DESCRIPTION.md
LICENSE.txt
MANIFEST.in
README.md
setup.py
src/cli/__init__.py
src/cli/cli.py
src/docker_jobber.egg-info/PKG-INFO
src/docker_jobber.egg-info/SOURCES.txt
src/docker_jobber.egg-info/dependency_links.txt
src/docker_jobber.egg-info/entry_points.txt
src/docker_jobber.egg-info/requires.txt
src/docker_jobber.egg-info/top_level.txt
src/jobber/Credentials.py
src/jobber/Jobber.py
src/jobber/__init__.py
src/jobber/config.py
src/tests/__init__.py
src/tests/test_image_url.py