Metadata-Version: 2.1
Name: docker-jobber
Version: 0.3.9
Summary: A command line interface (CLI) application for managing machine learning workflows using Docker
Home-page: https://github.com/mentice/docker-jobber
Author: Eric Parker
Author-email: eric.parker@mentice.com
License: UNKNOWN
Platform: UNKNOWN
Classifier: Programming Language :: Python :: 3
Classifier: License :: OSI Approved :: BSD License
Classifier: Operating System :: OS Independent
Classifier: Topic :: Scientific/Engineering :: Artificial Intelligence
